wbo/__init__.py
wbo/cli.py
wbo/main.py
wbo-0.0.7.3.dist-info/LICENSE.txt
wbo-0.0.7.3.dist-info/METADATA
wbo-0.0.7.3.dist-info/WHEEL
wbo-0.0.7.3.dist-info/entry_points.txt
wbo-0.0.7.3.dist-info/top_level.txt
wbo-0.0.7.3.dist-info/RECORD
