Metadata-Version: 2.1
Name: wbo
Version: 0.0.7.3
Summary: Download and plot worldwide box office data!
Home-page: UNKNOWN
Author: Adnan Hoq
License: UNKNOWN
Platform: UNKNOWN
Requires-Dist: pandas (==1.2.3)
Requires-Dist: plotly (==4.14.3)
Requires-Dist: click (==7.1.2)
Requires-Dist: lxml (==4.6.3)
